MANIFEST.in
README.rst
setup.py
swapietl/__init__.py
swapietl/cli.py
swapietl/models.py
swapietl/swapi_impl.py
swapietl.egg-info/PKG-INFO
swapietl.egg-info/SOURCES.txt
swapietl.egg-info/dependency_links.txt
swapietl.egg-info/entry_points.txt
swapietl.egg-info/requires.txt
swapietl.egg-info/top_level.txt