Metadata-Version: 2.1
Name: swapietl
Version: 0.0.1
Summary: Star Wars API ETL - YouGov
Home-page: https://github.com/dgarana/swapietl
Author: David Garaña
License: UNKNOWN
Platform: UNKNOWN
Classifier: Programming Language :: Python :: 3.7
